pigadm/__cartopy.py
pigadm/__core.py
pigadm/__curses_doc.py
pigadm/__doc.py
pigadm/__exec.py
pigadm/__init__.py
pigadm/__plot.py
pigadm/__release.py
pigadm-2.3.0.data/scripts/pigadm
pigadm-2.3.0.dist-info/LICENSE
pigadm-2.3.0.dist-info/METADATA
pigadm-2.3.0.dist-info/WHEEL
pigadm-2.3.0.dist-info/top_level.txt
pigadm-2.3.0.dist-info/RECORD
